usos_bridge/__init__.py
usos_bridge/auth.py
usos_bridge/client.py
usos_bridge/errors.py
usos_bridge/instance_config.py
usos_bridge/data/usos_instances.json
usos_bridge-0.0.1.dist-info/licenses/LICENSE
usos_bridge-0.0.1.dist-info/METADATA
usos_bridge-0.0.1.dist-info/WHEEL
usos_bridge-0.0.1.dist-info/top_level.txt
usos_bridge-0.0.1.dist-info/RECORD
