Metadata-Version: 2.4
Name: usos_bridge
Version: 0.0.1
Summary: Access the USOS API using your standard web credentials
Author-email: Piotr Ginał <ginal.piotr11@gmail.com>
License: MIT
Requires-Python: >=3.11
License-File: LICENSE
Requires-Dist: beautifulsoup4
Requires-Dist: httpx
Requires-Dist: pydantic
Requires-Dist: python-dotenv
Dynamic: license-file
